README.md
config.py.in
pyproject.toml
setup.cfg
setup.py
./CMakeLists.txt
./patches/g_comm.patch
./patches/operator.patch
./patches/sharedlib.patch
./patches/smearing.patch
lyncs_tmLQCD/__init__.py
lyncs_tmLQCD/base.py
lyncs_tmLQCD/config.py
lyncs_tmLQCD/gauge.py
lyncs_tmLQCD/lib.py
lyncs_tmLQCD/momenta.py
lyncs_tmLQCD/operator.py
lyncs_tmLQCD/rational.py
lyncs_tmLQCD/spinor.py
lyncs_tmLQCD.egg-info/PKG-INFO
lyncs_tmLQCD.egg-info/SOURCES.txt
lyncs_tmLQCD.egg-info/dependency_links.txt
lyncs_tmLQCD.egg-info/requires.txt
lyncs_tmLQCD.egg-info/top_level.txt
test/test_gauge.py
test/test_momenta.py
test/test_operator.py
test/test_rational.py
test/test_spinor.py