Metadata-Version: 2.1
Name: lyncs-tmLQCD
Version: 0.1.1
Summary: A Python interface to tmLQCD for Lyncs
Home-page: https://github.com/Lyncs-API/lyncs.tmLQCD
Author: Simone Bacchio
Author-email: s.bacchio@gmail.com
License: UNKNOWN
Project-URL: Source, https://github.com/Lyncs-API/lyncs.tmLQCD
Project-URL: Documentation, https://github.com/Lyncs-API/lyncs.tmLQCD/README.md
Project-URL: Tracker, https://github.com/Lyncs-API/lyncs.tmLQCD/issues
Project-URL: Download, https://github.com/Lyncs-API/lyncs.tmLQCD/archive/master.zip
Keywords: Lyncs,tmLQCD,Lattice QCD,Wilson,Twisted-mass,Clover,Fermions,HMC,Actions,ETMC
Platform: UNKNOWN
Classifier: Development Status :: 2 - Pre-Alpha
Classifier: Intended Audience :: Developers
Classifier: Intended Audience :: Education
Classifier: Intended Audience :: Science/Research
Classifier: License :: OSI Approved :: BSD License
Classifier: Natural Language :: English
Classifier: Operating System :: Unix
Classifier: Programming Language :: C
Classifier: Programming Language :: C++
Classifier: Programming Language :: Python :: 3 :: Only
Classifier: Topic :: Scientific/Engineering :: Physics
Provides-Extra: test
Provides-Extra: all
